ab_core/auth_client/__init__.py
ab_core/auth_client/oauth2/__init__.py
ab_core/auth_client/oauth2/client/__init__.py
ab_core/auth_client/oauth2/client/base.py
ab_core/auth_client/oauth2/client/pkce.py
ab_core/auth_client/oauth2/client/standard.py
ab_core/auth_client/oauth2/schema/__init__.py
ab_core/auth_client/oauth2/schema/authorize.py
ab_core/auth_client/oauth2/schema/client_type.py
ab_core/auth_client/oauth2/schema/exchange.py
ab_core/auth_client/oauth2/schema/oidc.py
ab_core/auth_client/oauth2/schema/refresh.py
ab_core/auth_client/oauth2/schema/token.py
ab_auth_client-0.1.13.dist-info/METADATA
ab_auth_client-0.1.13.dist-info/WHEEL
ab_auth_client-0.1.13.dist-info/licenses/LICENSE
ab_auth_client-0.1.13.dist-info/RECORD
