Metadata-Version: 2.4
Name: ab-auth-client
Version: 0.1.13
Author-email: Matthew Coulter <53892067+mattcoulter7@users.noreply.github.com>
License-File: LICENSE
Requires-Python: <4,>=3.12
Requires-Dist: ab-cache<0.2.0,>=0.1.3
Requires-Dist: ab-pkce<0.2.0,>=0.1.3
Requires-Dist: httpx>=0.28.1
Requires-Dist: pydantic<3,>=2.11.7
Requires-Dist: requests<3,>=2.32.4
Requires-Dist: yarl<2,>=1.20.1
